<?xml version="1.0" encoding="UTF-8"?>
<StructureDefinition xmlns="http://hl7.org/fhir">
    <id value="au-deliverypointidentifier" />
    <extension url="http://hl7.org/fhir/StructureDefinition/structuredefinition-fmm">
        <valueInteger value="2"/> 
    </extension>
    <url value="http://hl7.org.au/fhir/StructureDefinition/au-deliverypointidentifier" />
    <name value="AUDeliveryPointIdentifier" />
    <title value="AU Delivery Point Identifier" />
    <status value="draft" />
    <description value="This identifier profile defines an Australia Post Delivery Point Identifier (DPID) in an Australian context (see [Australia Post](https://auspost.com.au/content/dam/auspost_corp/media/documents/australia-post-data-guide.pdf) for further information). A DPID is a randomly generated, unique 8-digit number, allocated by Australia Post to an address. A DPID enables each delivery point in Australia to be uniquely identified." />
    <kind value="complex-type" />
    <abstract value="false" />
    <type value="Identifier" />
    <baseDefinition value="http://hl7.org/fhir/StructureDefinition/Identifier" />
    <derivation value="constraint" />
    <differential>
        <element id="Identifier">
            <path value="Identifier"/>
            <short value="Australia Post Delivery Point Identifier (DPID)"/>
            <definition value="Australia Post Delivery Point Identifier (DPID) allocated to a location address. A DPID enables each delivery point in Australia to be uniquely identified." />
            <constraint>
                <key value="inv-dpid-0"/>
                <severity value="error"/>
                <human value="DPID shall be 8 digits"/>
                <expression value="value.matches(&#39;^([0-9]{8})$&#39;)"/>
            </constraint>
        </element>
        <element id="Identifier.type">
            <path value="Identifier.type" />
            <short value="Coded identifier type for DPID" />
            <min value="1" />
            <patternCodeableConcept>
                <coding>
                    <system value="http://terminology.hl7.org.au/CodeSystem/v2-0203" />
                    <code value="DPID" />
                </coding>
            </patternCodeableConcept>
        </element>
        <element id="Identifier.system">
            <path value="Identifier.system"/>
            <min value="1"/>
            <fixedUri value="http://hl7.org.au/id/dpid"/>
        </element>
        <element id="Identifier.value">
            <path value="Identifier.value"/>
            <short value="DPID"/>
            <comment value="This concept is equivalent to Australian Institute of Health and Welfare data element 287218 [Postal delivery point identifier {N(8)}](https://meteor.aihw.gov.au/content/index.phtml/itemId/287218)." />
            <min value="1"/>
            <example>
                <label value="DPID" />
                <valueString value="34567890" />
            </example>
        </element>
    </differential>
</StructureDefinition>
