{
  "resourceType" : "Patient",
  "id" : "address-example1",
  "text" : {
    "status" : "generated",
    "div" : "<div xmlns=\"http://www.w3.org/1999/xhtml\"><p class=\"res-header-id\"><b>Generated Narrative: Patient address-example1</b></p><a name=\"address-example1\"> </a><a name=\"hcaddress-example1\"> </a><p style=\"border: 1px #661aff solid; background-color: #e6e6ff; padding: 10px;\">Anonymous Patient (no stated gender), DoB Unknown</p><hr/><table class=\"grid\"><tr><td style=\"background-color: #f3f5da\" title=\"Ways to contact the Patient\">Contact Detail</td><td colspan=\"3\">Level 1, 300 George St, Brisbane, QLD 4000</td></tr></table></div>"
  },
  "address" : [{
    "text" : "Level 1, 300 George St, Brisbane, QLD 4000",
    "line" : ["Level 1 300 George St"],
    "city" : "Brisbane",
    "state" : "QLD",
    "postalCode" : "4000",
    "country" : "AU"
  }]
}