<?xml version="1.0" encoding="utf-8"?>
<StructureDefinition xmlns="http://hl7.org/fhir">
  <url value="http://hl7.org.au/fhir/StructureDefinition/au-parity" />
  <name value="AUParity" />
  <title value="AU Parity" />
  <status value="draft" />
  <jurisdiction>
    <coding>
      <system value="urn:iso:std:iso:3166" />
      <code value="AU" />
    </coding>
  </jurisdiction>
  <fhirVersion value="4.0.1" />
  <kind value="resource" />
  <abstract value="false" />
  <type value="Observation" />
  <baseDefinition value="http://hl7.org/fhir/StructureDefinition/Observation" />
  <derivation value="constraint" />
  <differential>
    <element id="Observation.status">
      <path value="Observation.status" />
      <fixedCode value="final" />
    </element>
    <element id="Observation.code.coding">
      <path value="Observation.code.coding" />
      <slicing>
        <discriminator>
          <type value="value" />
          <path value="code" />
        </discriminator>
        <discriminator>
          <type value="value" />
          <path value="system" />
        </discriminator>
        <rules value="open" />
      </slicing>
      <min value="1" />
      <patternCoding>
        <system value="http://snomed.info/sct" />
        <code value="364325004" />
      </patternCoding>
    </element>
    <element id="Observation.code.coding:parityLOINCCode">
      <path value="Observation.code.coding" />
      <sliceName value="parityLOINCCode" />
      <max value="1" />
      <patternCoding>
        <system value="http://loinc.org" />
        <code value="11977-6" />
      </patternCoding>
    </element>
    <element id="Observation.subject">
      <path value="Observation.subject" />
      <min value="1" />
      <type>
        <code value="Reference" />
        <targetProfile value="http://hl7.org/fhir/StructureDefinition/Patient" />
      </type>
    </element>
    <element id="Observation.effective[x]">
      <path value="Observation.effective[x]" />
      <min value="1" />
      <type>
        <code value="dateTime" />
      </type>
      <type>
        <code value="Period" />
      </type>
    </element>
    <element id="Observation.value[x]">
      <path value="Observation.value[x]" />
      <min value="1" />
      <type>
        <code value="Quantity" />
      </type>
      <constraint>
        <key value="inv0-parity" />
        <severity value="error" />
        <human value="Parity must be a whole number" />
        <expression value="value.toString().contains('.').not()" />
        <source value="http://hl7.org.au/fhir/StructureDefinition/au-parity" />
      </constraint>
    </element>
    <element id="Observation.value[x].system">
      <path value="Observation.value[x].system" />
      <min value="1" />
      <fixedUri value="http://unitsofmeasure.org" />
    </element>
    <element id="Observation.value[x].code">
      <path value="Observation.value[x].code" />
      <min value="1" />
      <fixedCode value="1" />
    </element>
  </differential>
</StructureDefinition>