{
  "resourceType" : "ValueSet",
  "id" : "medicine-item-change",
  "meta" : {
    "profile" : ["https://healthterminologies.gov.au/fhir/StructureDefinition/composed-value-set-4"]
  },
  "text" : {
    "status" : "generated",
    "div" : "<div xmlns=\"http://www.w3.org/1999/xhtml\"><p class=\"res-header-id\"><b>Generated Narrative: ValueSet medicine-item-change</b></p><a name=\"medicine-item-change\"> </a><a name=\"hcmedicine-item-change\"> </a><div style=\"display: inline-block; background-color: #d9e0e7; padding: 6px; margin: 4px; border: 1px solid #8da1b4; border-radius: 5px; line-height: 60%\"><p style=\"margin-bottom: 0px\"/><p style=\"margin-bottom: 0px\">Profile: <code>https://healthterminologies.gov.au/fhir/StructureDefinition/composed-value-set-4</code></p></div><ul><li>Include all codes defined in <a href=\"CodeSystem-medicine-item-change.html\"><code>http://terminology.hl7.org.au/CodeSystem/medicine-item-change</code></a><span title=\"Version is not explicitly stated, which means it is fixed to the version provided in this specification\"> version &#x1F4E6;6.0.1-ci-build</span></li></ul></div>"
  },
  "extension" : [{
    "url" : "http://hl7.org/fhir/StructureDefinition/structuredefinition-fmm",
    "valueInteger" : 1
  },
  {
    "url" : "http://hl7.org/fhir/StructureDefinition/structuredefinition-standards-status",
    "valueCode" : "trial-use",
    "_valueCode" : {
      "extension" : [{
        "url" : "http://hl7.org/fhir/StructureDefinition/structuredefinition-conformance-derivedFrom",
        "valueCanonical" : "http://hl7.org.au/fhir/ImplementationGuide/hl7.fhir.au.base"
      }]
    }
  }],
  "url" : "http://terminology.hl7.org.au/ValueSet/medicine-item-change",
  "identifier" : [{
    "system" : "urn:ietf:rfc:3986",
    "value" : "urn:oid:2.16.840.1.113883.2.3.4.2.4.6"
  }],
  "version" : "6.0.1-ci-build",
  "name" : "MedicineItemChange",
  "title" : "Medicine Item Change",
  "status" : "active",
  "experimental" : false,
  "date" : "2026-06-19T03:25:57+00:00",
  "publisher" : "HL7 Australia",
  "contact" : [{
    "name" : "HL7 Australia FHIR Working Group",
    "telecom" : [{
      "system" : "url",
      "value" : "https://confluence.hl7.org/display/HAFWG",
      "use" : "work"
    }]
  }],
  "description" : "The Medicine Item Change value set includes values that may be used to identify that a change that has been made, or is recommended to be made, to a medicine item.",
  "jurisdiction" : [{
    "coding" : [{
      "system" : "urn:iso:std:iso:3166",
      "code" : "AU"
    }]
  }],
  "copyright" : "HL7 Australia© 2018+; Licensed Under Creative Commons No Rights Reserved.",
  "compose" : {
    "include" : [{
      "system" : "http://terminology.hl7.org.au/CodeSystem/medicine-item-change"
    }]
  }
}